<?xml version="1.0" encoding="utf-8"?>
<Empresas>
  <Empresa id="126722">
    <!--Dados gerais da empresa (recebidos da RFB)-->
    <CNPJ>15253439000101</CNPJ>
    <NomeEmpresarial>CONSTRUMAX PRESTACAO DE SERVICOS LTDA - ME</NomeEmpresarial>
    <SituacaoCadastral>02</SituacaoCadastral>
    <DataSituacaoCadastral>2012-03-16</DataSituacaoCadastral>
    <NaturezaJuridica>2062</NaturezaJuridica>
    <DataAbertura>2012-03-16</DataAbertura>
    <Porte>01</Porte>
    <!--Dados gerais da empresa (coletados do usuário)-->
    <NumeroRegistro>35226438821</NumeroRegistro>
    <TipoRegistro>1</TipoRegistro>
    <TipoMEI>0</TipoMEI>
    <!--Dados do responsável pela empresa (conforme RFB)-->
    <CPFResponsavel>20055561810</CPFResponsavel>
    <NomeResponsavel>RICARDO MASSARO CALAROTA</NomeResponsavel>
    <DDD1>16</DDD1>
    <Telefone1>91510808</Telefone1>
    <Email>ricardomassaro@yahoo.com.br</Email>
    <!--Endereço do estabelecimento-->
    <Endereco>
      <SetorQuadraLote>02880</SetorQuadraLote>
      <TipoLogradouro>Rua</TipoLogradouro>
      <Logradouro>MAESTRO GROSSI</Logradouro>
      <NumeroLogradouro>411</NumeroLogradouro>
      <Bairro>NOVA JABOTICABAL</Bairro>
      <CEP>14887036</CEP>
      <UF>SP</UF>
      <Municipio Concla="24303" rfb="279">Jaboticabal</Municipio>
    </Endereco>
    <!--Atividades cadastradas e exercidas pela empresa (CNAE e auxiliares)-->
    <Atividades>
      <CNAE codigo="4321500" principal="1" exercida="1" />
      <CNAE codigo="4322301" principal="0" exercida="1" />
      <CNAE codigo="4330402" principal="0" exercida="1" />
      <CNAE codigo="4330405" principal="0" exercida="1" />
      <CNAE codigo="4330499" principal="0" exercida="1" />
      <CNAE codigo="4399199" principal="0" exercida="1" />
      <CNAE codigo="4744099" principal="0" exercida="1" />
      <CNAE codigo="9529105" principal="0" exercida="1" />
      <Auxiliar id="10" />
    </Atividades>
    <!--QSA da empresa-->
    <Sociedade>
      <Socio>
        <Tipo>2</Tipo>
        <Nome>RICARDO MASSARO CALAROTA</Nome>
        <Numero>00020055561810</Numero>
        <CodigoPaisOrigem>000</CodigoPaisOrigem>
      </Socio>
      <Socio>
        <Tipo>2</Tipo>
        <Nome>MARA SILVIA MASSARO CALAROTA</Nome>
        <Numero>00002054055840</Numero>
        <CodigoPaisOrigem>000</CodigoPaisOrigem>
      </Socio>
      <Socio>
        <Tipo>2</Tipo>
        <Nome>ALINE MASSARO CALAROTA</Nome>
        <Numero>00020055559832</Numero>
        <CodigoPaisOrigem>000</CodigoPaisOrigem>
      </Socio>
    </Sociedade>
    <!--Dados do contador-->
    <ClassificacaoCRCContadorPJ>0</ClassificacaoCRCContadorPJ>
    <NumeroCRCContadorPJ>000000</NumeroCRCContadorPJ>
    <CNPJContador>00000000000000</CNPJContador>
    <TipoCRCContadorPF>O</TipoCRCContadorPF>
    <ClassificacaoCRCContadorPF>1</ClassificacaoCRCContadorPF>
    <NumeroCRCContadorPF>065569</NumeroCRCContadorPF>
    <UFCRCContadorPF>SP</UFCRCContadorPF>
    <CPFContador>28203593887</CPFContador>
    <!--Viabilidade-->
    <Viabilidade id="1056633">
      <Solicitacao id="231034">231034201492</Solicitacao>
      <Status id="12" />
      <DataStatus>2014-03-20T00:00:00</DataStatus>
      <RestricaoOperacao id="2977" />
      <RestricaoOperacao id="2977" />
      <RestricaoOperacao id="2977" />
    </Viabilidade>
    <!--Licenciamentos (um bloco abaixo para cada órgão)-->
    <Licenciamento id="1056631">
      <Solicitacao id="231034">231034201492</Solicitacao>
      <Orgao id="3" />
      <Status id="5" />
      <Risco id="0" />
      <Numero>231034201492</Numero>
      <DataEmissao>2014-03-19T00:00:00</DataEmissao>
      <DataVencimento>2017-03-19T00:00:00</DataVencimento>
      <Pergunta id="4276" resposta="0" />
      <Pergunta id="4277" resposta="0" />
      <Pergunta id="4278" resposta="0" />
      <Pergunta id="4280" resposta="0" />
      <Pergunta id="4281" resposta="0" />
      <Pergunta id="4282" resposta="0" />
      <Declaracao id="6345" />
      <Declaracao id="6346" />
      <Declaracao id="6347" />
      <Declaracao id="6349" />
      <Declaracao id="6350" />
      <Declaracao id="6351" />
      <Declaracao id="6352" />
      <Declaracao id="6353" />
      <Declaracao id="6354" />
      <Declaracao id="6355" />
      <Imovel>
        <AreaEstabelecimento>137</AreaEstabelecimento>
        <NomeProprietario>IVO RIVA FILHO</NomeProprietario>
        <EmailProprietario>jaboticabal@doutorresolve.com.br</EmailProprietario>
        <TelefoneProprietario>1632021253</TelefoneProprietario>
        <NomeResponsavelUso>RICARDO MASSARO CALAROTA</NomeResponsavelUso>
        <TelefoneResponsavelUso>1632021253</TelefoneResponsavelUso>
        <AreaTotal>137</AreaTotal>
        <Pavimentos>1</Pavimentos>
        <Contiguo>0</Contiguo>
        <OutrosUsos>0</OutrosUsos>
      </Imovel>
    </Licenciamento>
    <Licenciamento id="1056629">
      <Solicitacao id="231034">231034201492</Solicitacao>
      <Orgao id="1" />
      <Status id="5" />
      <Risco id="0" />
      <Numero>231034201492</Numero>
      <DataEmissao>2014-03-19T00:00:00</DataEmissao>
      <DataVencimento>2015-03-19T00:00:00</DataVencimento>
    </Licenciamento>
    <Licenciamento id="1056630">
      <Solicitacao id="231034">231034201492</Solicitacao>
      <Orgao id="2" />
      <Status id="5" />
      <Risco id="0" />
      <Numero>231034201492</Numero>
      <DataEmissao>2014-03-19T00:00:00</DataEmissao>
      <DataVencimento>2019-03-19T00:00:00</DataVencimento>
      <Declaracao id="6288" />
    </Licenciamento>
    <Licenciamento id="1056632">
      <Solicitacao id="231034">231034201492</Solicitacao>
      <Orgao id="287" />
      <Status id="5" />
      <Risco id="0" />
      <Numero>231034201492</Numero>
      <DataEmissao>2014-03-19T00:00:00</DataEmissao>
      <DataVencimento>2015-03-19T00:00:00</DataVencimento>
    </Licenciamento>
  </Empresa>
  <Empresa id="126754">
    <!--Dados gerais da empresa (recebidos da RFB)-->
    <CNPJ>15210806000181</CNPJ>
    <NomeEmpresarial>OLIVEIRA &amp;amp; SOUZA MACEDO BAR LTDA  - ME</NomeEmpresarial>
    <SituacaoCadastral>02</SituacaoCadastral>
    <DataSituacaoCadastral>2012-03-09</DataSituacaoCadastral>
    <NaturezaJuridica>2062</NaturezaJuridica>
    <DataAbertura>2012-03-09</DataAbertura>
    <Porte>01</Porte>
    <!--Dados gerais da empresa (coletados do usuário)-->
    <NumeroRegistro>35228159015</NumeroRegistro>
    <TipoRegistro>1</TipoRegistro>
    <TipoMEI>0</TipoMEI>
    <!--Dados do responsável pela empresa (conforme RFB)-->
    <CPFResponsavel>38467227826</CPFResponsavel>
    <NomeResponsavel>JESSICA ALESSANDRA DE OLIVEIRA</NomeResponsavel>
    <DDD1>16</DDD1>
    <Telefone1>97862065</Telefone1>
    <DDD2>16</DDD2>
    <Telefone2>81731347</Telefone2>
    <Email>orgatec_contab@terra.com.br</Email>
    <!--Endereço do estabelecimento-->
    <Endereco>
      <SetorQuadraLote>3@</SetorQuadraLote>
      <TipoLogradouro>Rodovia</TipoLogradouro>
      <Logradouro>JOSE PIZARRO/SP 305</Logradouro>
      <NumeroLogradouro>S/N</NumeroLogradouro>
      <Complemento>CXPST 504</Complemento>
      <Bairro>RURAL</Bairro>
      <CEP>14870970</CEP>
      <UF>SP</UF>
      <Municipio Concla="24303" rfb="279">Jaboticabal</Municipio>
    </Endereco>
    <!--Atividades cadastradas e exercidas pela empresa (CNAE e auxiliares)-->
    <Atividades>
      <CNAE codigo="5611202" principal="1" exercida="1" />
      <CNAE codigo="5611203" principal="0" exercida="1" />
    </Atividades>
    <!--QSA da empresa-->
    <Sociedade>
      <Socio>
        <Tipo>2</Tipo>
        <Nome>JESSICA ALESSANDRA DE OLIVEIRA</Nome>
        <Numero>00038467227826</Numero>
        <CodigoPaisOrigem>000</CodigoPaisOrigem>
      </Socio>
      <Socio>
        <Tipo>2</Tipo>
        <Nome>JOSINETE DE SOUZA MACEDO</Nome>
        <Numero>00058052291534</Numero>
        <CodigoPaisOrigem>000</CodigoPaisOrigem>
      </Socio>
    </Sociedade>
    <!--Dados do contador-->
    <ClassificacaoCRCContadorPJ>0</ClassificacaoCRCContadorPJ>
    <NumeroCRCContadorPJ>000000</NumeroCRCContadorPJ>
    <CNPJContador>00000000000000</CNPJContador>
    <TipoCRCContadorPF>O</TipoCRCContadorPF>
    <ClassificacaoCRCContadorPF>1</ClassificacaoCRCContadorPF>
    <NumeroCRCContadorPF>190090</NumeroCRCContadorPF>
    <UFCRCContadorPF>SP</UFCRCContadorPF>
    <CPFContador>13855314870</CPFContador>
    <!--Viabilidade-->
    <Viabilidade id="1056972">
      <Solicitacao id="231109">231109201492</Solicitacao>
      <Status id="12" />
      <DataStatus>2014-03-20T00:00:00</DataStatus>
      <RestricaoOperacao id="2977" />
      <RestricaoOperacao id="2977" />
    </Viabilidade>
    <!--Licenciamentos (um bloco abaixo para cada órgão)-->
    <Licenciamento id="1056970">
      <Solicitacao id="231109">231109201492</Solicitacao>
      <Orgao id="3" />
      <Status id="5" />
      <Risco id="0" />
      <Numero>880080</Numero>
      <DataEmissao>2014-03-19T00:00:00</DataEmissao>
      <DataVencimento>2014-06-01T00:00:00</DataVencimento>
      <Pergunta id="4276" resposta="0" />
      <Pergunta id="4277" resposta="0" />
      <Pergunta id="4278" resposta="0" />
      <Pergunta id="4279" resposta="0" />
      <Pergunta id="4280" resposta="0" />
      <Pergunta id="4281" resposta="0" />
      <Pergunta id="4282" resposta="0" />
      <Declaracao id="6345" />
      <Declaracao id="6346" />
      <Declaracao id="6347" />
      <Declaracao id="6348" />
      <Declaracao id="6349" />
      <Declaracao id="6350" />
      <Declaracao id="6351" />
      <Declaracao id="6352" />
      <Declaracao id="6353" />
      <Declaracao id="6354" />
      <Declaracao id="6355" />
      <Imovel>
        <AreaEstabelecimento>80</AreaEstabelecimento>
        <NomeProprietario>JESSICA ALESSANDRA DE OLIVEIRA</NomeProprietario>
        <EmailProprietario>orgatec_contab@terra.com.br</EmailProprietario>
        <TelefoneProprietario>1632026252</TelefoneProprietario>
        <NomeResponsavelUso>OLIVEIRA &amp; SOUZA MACEDO BAR LTDA - ME</NomeResponsavelUso>
        <TelefoneResponsavelUso>1697862065</TelefoneResponsavelUso>
        <AreaTotal>80</AreaTotal>
        <Pavimentos>1</Pavimentos>
        <Contiguo>0</Contiguo>
        <OutrosUsos>0</OutrosUsos>
        <NumeroAVCB>880080</NumeroAVCB>
        <ValidadeAVCB>2014-06-01</ValidadeAVCB>
      </Imovel>
    </Licenciamento>
    <Licenciamento id="1056968">
      <Solicitacao id="231109">231109201492</Solicitacao>
      <Orgao id="1" />
      <Status id="5" />
      <Risco id="0" />
      <Numero>231109201492</Numero>
      <DataEmissao>2014-03-19T00:00:00</DataEmissao>
      <DataVencimento>2015-03-19T00:00:00</DataVencimento>
    </Licenciamento>
    <Licenciamento id="1056969">
      <Solicitacao id="231109">231109201492</Solicitacao>
      <Orgao id="2" />
      <Status id="5" />
      <Risco id="0" />
      <Numero>231109201492</Numero>
      <DataEmissao>2014-03-19T00:00:00</DataEmissao>
      <DataVencimento>2019-03-19T00:00:00</DataVencimento>
      <Declaracao id="6288" />
    </Licenciamento>
    <Licenciamento id="1056971">
      <Solicitacao id="231109">231109201492</Solicitacao>
      <Orgao id="287" />
      <Status id="5" />
      <Risco id="0" />
      <Numero>231109201492</Numero>
      <DataEmissao>2014-03-19T00:00:00</DataEmissao>
      <DataVencimento>2015-03-19T00:00:00</DataVencimento>
      <Pergunta id="4284" resposta="0" />
      <Declaracao id="6359" />
      <Declaracao id="6363" />
      <Declaracao id="6367" />
    </Licenciamento>
  </Empresa>
  <Empresa id="126849">
    <!--Dados gerais da empresa (recebidos da RFB)-->
    <CNPJ>19862088000189</CNPJ>
    <NomeEmpresarial>BEDIM REPRESENTACOES S/S LTDA</NomeEmpresarial>
    <SituacaoCadastral>02</SituacaoCadastral>
    <DataSituacaoCadastral>2014-03-07</DataSituacaoCadastral>
    <NaturezaJuridica>2240</NaturezaJuridica>
    <DataAbertura>2014-03-07</DataAbertura>
    <Porte>05</Porte>
    <!--Dados gerais da empresa (coletados do usuário)-->
    <NumeroRegistro>4023</NumeroRegistro>
    <TipoRegistro>2</TipoRegistro>
    <TipoMEI>0</TipoMEI>
    <!--Dados do responsável pela empresa (conforme RFB)-->
    <CPFResponsavel>31824440855</CPFResponsavel>
    <NomeResponsavel>DIEIMES UILIAM BEDIM</NomeResponsavel>
    <DDD1>16</DDD1>
    <Telefone1>32031376</Telefone1>
    <DDD2>16</DDD2>
    <Telefone2>32033538</Telefone2>
    <Email>RH@OCPOLACHINI.COM.BR</Email>
    <!--Endereço do estabelecimento-->
    <Endereco>
      <SetorQuadraLote>30195</SetorQuadraLote>
      <TipoLogradouro>Rua</TipoLogradouro>
      <Logradouro>DOUTOR MARIO DE CAMPOS</Logradouro>
      <NumeroLogradouro>1401</NumeroLogradouro>
      <Complemento>CASA: 02;</Complemento>
      <Bairro>JARDIM SAO MARCOS I</Bairro>
      <CEP>14887200</CEP>
      <UF>SP</UF>
      <Municipio Concla="24303" rfb="279">Jaboticabal</Municipio>
    </Endereco>
    <!--Atividades cadastradas e exercidas pela empresa (CNAE e auxiliares)-->
    <Atividades>
      <CNAE codigo="8299799" principal="1" exercida="1" />
    </Atividades>
    <!--QSA da empresa-->
    <Sociedade>
      <Socio>
        <Tipo>2</Tipo>
        <Nome>DIEIMES UILIAM BEDIM</Nome>
        <Numero>00031824440855</Numero>
        <CodigoPaisOrigem>000</CodigoPaisOrigem>
      </Socio>
      <Socio>
        <Tipo>2</Tipo>
        <Nome>ROSMARI APARECIDA FERNANDES BEDIM</Nome>
        <Numero>00025546322861</Numero>
        <CodigoPaisOrigem>000</CodigoPaisOrigem>
      </Socio>
    </Sociedade>
    <!--Dados do contador-->
    <ClassificacaoCRCContadorPJ>0</ClassificacaoCRCContadorPJ>
    <NumeroCRCContadorPJ>000000</NumeroCRCContadorPJ>
    <CNPJContador>00000000000000</CNPJContador>
    <TipoCRCContadorPF>O</TipoCRCContadorPF>
    <ClassificacaoCRCContadorPF>1</ClassificacaoCRCContadorPF>
    <NumeroCRCContadorPF>184051</NumeroCRCContadorPF>
    <UFCRCContadorPF>SP</UFCRCContadorPF>
    <CPFContador>13888349877</CPFContador>
    <!--Viabilidade-->
    <Viabilidade id="1057878">
      <Solicitacao id="231316">231316201400</Solicitacao>
      <Status id="12" />
      <DataStatus>2014-03-20T00:00:00</DataStatus>
      <RestricaoOperacao id="2961" />
      <RestricaoOperacao id="2961" />
      <RestricaoOperacao id="2961" />
    </Viabilidade>
    <!--Licenciamentos (um bloco abaixo para cada órgão)-->
    <Licenciamento id="1057876">
      <Solicitacao id="231316">231316201400</Solicitacao>
      <Orgao id="3" />
      <Status id="5" />
      <Risco id="0" />
      <Numero>231316201400</Numero>
      <DataEmissao>2014-03-20T00:00:00</DataEmissao>
      <DataVencimento>2017-03-20T00:00:00</DataVencimento>
      <Pergunta id="4282" resposta="0" />
      <Pergunta id="4276" resposta="0" />
      <Pergunta id="4277" resposta="0" />
      <Pergunta id="4278" resposta="0" />
      <Pergunta id="4280" resposta="0" />
      <Pergunta id="4281" resposta="0" />
      <Declaracao id="6352" />
      <Declaracao id="6353" />
      <Declaracao id="6354" />
      <Declaracao id="6355" />
      <Declaracao id="6345" />
      <Declaracao id="6346" />
      <Declaracao id="6347" />
      <Declaracao id="6349" />
      <Declaracao id="6350" />
      <Declaracao id="6351" />
      <Imovel>
        <AreaEstabelecimento>21</AreaEstabelecimento>
        <NomeProprietario>MONICA DE BIAGI CURTARELLI</NomeProprietario>
        <EmailProprietario>RH@OCPOLACHINI.COM.BR</EmailProprietario>
        <TelefoneProprietario>1632033538</TelefoneProprietario>
        <NomeResponsavelUso>BEDIM REPRESENTAÇÕES S/S LTDA</NomeResponsavelUso>
        <TelefoneResponsavelUso>1632033538</TelefoneResponsavelUso>
        <AreaTotal>411</AreaTotal>
        <Pavimentos>1</Pavimentos>
        <Contiguo>0</Contiguo>
        <OutrosUsos>0</OutrosUsos>
      </Imovel>
    </Licenciamento>
    <Licenciamento id="1057874">
      <Solicitacao id="231316">231316201400</Solicitacao>
      <Orgao id="1" />
      <Status id="5" />
      <Risco id="0" />
      <Numero>231316201400</Numero>
      <DataEmissao>2014-03-20T00:00:00</DataEmissao>
      <DataVencimento>2015-03-20T00:00:00</DataVencimento>
    </Licenciamento>
    <Licenciamento id="1057875">
      <Solicitacao id="231316">231316201400</Solicitacao>
      <Orgao id="2" />
      <Status id="5" />
      <Risco id="0" />
      <Numero>231316201400</Numero>
      <DataEmissao>2014-03-20T00:00:00</DataEmissao>
      <DataVencimento>2019-03-20T00:00:00</DataVencimento>
      <Declaracao id="6288" />
    </Licenciamento>
    <Licenciamento id="1057877">
      <Solicitacao id="231316">231316201400</Solicitacao>
      <Orgao id="287" />
      <Status id="5" />
      <Risco id="0" />
      <Numero>231316201400</Numero>
      <DataEmissao>2014-03-20T00:00:00</DataEmissao>
      <DataVencimento>2015-03-20T00:00:00</DataVencimento>
    </Licenciamento>
  </Empresa>
</Empresas>